README.md
setup.py
SearchPolicies/DynamicProgramming.py
SearchPolicies/__init__.py
grid_navigation_policy.egg-info/PKG-INFO
grid_navigation_policy.egg-info/SOURCES.txt
grid_navigation_policy.egg-info/dependency_links.txt
grid_navigation_policy.egg-info/not-zip-safe
grid_navigation_policy.egg-info/top_level.txt