Metadata-Version: 1.0
Name: grid-navigation-policy
Version: 0.1
Summary: 2D Grid Navigation
Home-page: UNKNOWN
Author: UNKNOWN
Author-email: UNKNOWN
License: UNKNOWN
Platform: UNKNOWN
